{
  "feature_aucs": {
    "temperature_living_room": {
      "auc": 0.40273156542009525,
      "auc_std": 0.14621160811822037,
      "mean": 26.922309999999996,
      "std": 2.983925797318023,
      "min": 20.51,
      "max": 41.18,
      "missing_rate": 0.0,
      "zero_rate": 0.0,
      "unique_values": 627
    },
    "window_open": {
      "auc": 0.5850550895578889,
      "auc_std": 0.06866872522999098,
      "mean": 0.254,
      "std": 0.4352975993501457,
      "min": 0.0,
      "max": 1.0,
      "missing_rate": 0.0,
      "zero_rate": 0.746,
      "unique_values": 2
    },
    "power_consumption_fridge": {
      "auc": 0.4176545595823953,
      "auc_std": 0.16186544600039665,
      "mean": 156.60663,
      "std": 27.170117911836524,
      "min": 3.81,
      "max": 423.92,
      "missing_rate": 0.0,
      "zero_rate": 0.0,
      "unique_values": 851
    },
    "motion_detected_hallway": {
      "auc": 0.6647506525074216,
      "auc_std": 0.03476698102794153,
      "mean": 0.254,
      "std": 0.43529759935014567,
      "min": 0.0,
      "max": 1.0,
      "missing_rate": 0.0,
      "zero_rate": 0.746,
      "unique_values": 2
    },
    "door_state_front": {
      "auc": 0.6031758681835389,
      "auc_std": 0.04016077381342232,
      "mean": 0.031,
      "std": 0.17331762749357033,
      "min": 0.0,
      "max": 1.0,
      "missing_rate": 0.0,
      "zero_rate": 0.969,
      "unique_values": 2
    },
    "hour": {
      "auc": 0.49176147118009206,
      "auc_std": 0.10153563914979027,
      "mean": 11.345,
      "std": 7.083641365851323,
      "min": 0.0,
      "max": 23.0,
      "missing_rate": 0.0,
      "zero_rate": 0.052,
      "unique_values": 24
    },
    "day_of_week": {
      "auc": 0.6320555478073758,
      "auc_std": 0.25393360736836323,
      "mean": 3.031,
      "std": 2.0420673348349703,
      "min": 0.0,
      "max": 6.0,
      "missing_rate": 0.0,
      "zero_rate": 0.157,
      "unique_values": 7
    },
    "month": {
      "auc": 0.5,
      "auc_std": 0.0,
      "mean": 12.0,
      "std": 0.0,
      "min": 12.0,
      "max": 12.0,
      "missing_rate": 0.0,
      "zero_rate": 0.0,
      "unique_values": 1
    },
    "day_of_year": {
      "auc": 0.7925823354784722,
      "auc_std": 0.035916534917411945,
      "mean": 342.25,
      "std": 4.089926649709014,
      "min": 336.0,
      "max": 349.0,
      "missing_rate": 0.0,
      "zero_rate": 0.0,
      "unique_values": 14
    },
    "hour_sin": {
      "auc": 0.38218007212448446,
      "auc_std": 0.16171019932948344,
      "mean": 0.005365609431077719,
      "std": 0.7003271167923021,
      "min": -1.0,
      "max": 1.0,
      "missing_rate": 0.0,
      "zero_rate": 0.052,
      "unique_values": 22
    },
    "hour_cos": {
      "auc": 0.5933633519953777,
      "auc_std": 0.17373724114444788,
      "mean": 0.03757014547968543,
      "std": 0.7128124745607709,
      "min": -1.0,
      "max": 1.0,
      "missing_rate": 0.0,
      "zero_rate": 0.0,
      "unique_values": 22
    },
    "day_of_week_sin": {
      "auc": 0.3712518180550298,
      "auc_std": 0.24754178951755612,
      "mean": -0.03222509192339525,
      "std": 0.7000236392555488,
      "min": -0.9749279121818236,
      "max": 0.9749279121818236,
      "missing_rate": 0.0,
      "zero_rate": 0.157,
      "unique_values": 7
    },
    "day_of_week_cos": {
      "auc": 0.3389950389512064,
      "auc_std": 0.20145305916063505,
      "mean": 0.018192021471630057,
      "std": 0.7131602192275743,
      "min": -0.9009688679024191,
      "max": 1.0,
      "missing_rate": 0.0,
      "zero_rate": 0.0,
      "unique_values": 7
    },
    "month_sin": {
      "auc": 0.5,
      "auc_std": 0.0,
      "mean": -0.5000000000000002,
      "std": 2.220446049250313e-16,
      "min": -0.5000000000000004,
      "max": -0.5000000000000004,
      "missing_rate": 0.0,
      "zero_rate": 0.0,
      "unique_values": 1
    },
    "month_cos": {
      "auc": 0.5,
      "auc_std": 0.0,
      "mean": 0.8660254037844382,
      "std": 2.220446049250313e-16,
      "min": 0.8660254037844384,
      "max": 0.8660254037844384,
      "missing_rate": 0.0,
      "zero_rate": 0.0,
      "unique_values": 1
    },
    "is_weekend": {
      "auc": 0.6315574505389413,
      "auc_std": 0.20025756719324647,
      "mean": 0.298,
      "std": 0.4573794923255742,
      "min": 0.0,
      "max": 1.0,
      "missing_rate": 0.0,
      "zero_rate": 0.702,
      "unique_values": 2
    },
    "is_night": {
      "auc": 0.5584467334781137,
      "auc_std": 0.15968486420489392,
      "mean": 0.361,
      "std": 0.4802905370710524,
      "min": 0.0,
      "max": 1.0,
      "missing_rate": 0.0,
      "zero_rate": 0.639,
      "unique_values": 2
    },
    "is_business_hours": {
      "auc": 0.4252057141718635,
      "auc_std": 0.06466937412700892,
      "mean": 0.236,
      "std": 0.42462218500686,
      "min": 0.0,
      "max": 1.0,
      "missing_rate": 0.0,
      "zero_rate": 0.764,
      "unique_values": 2
    },
    "is_peak_hours": {
      "auc": 0.560728018967544,
      "auc_std": 0.11254744261343512,
      "mean": 0.168,
      "std": 0.3738662862575335,
      "min": 0.0,
      "max": 1.0,
      "missing_rate": 0.0,
      "zero_rate": 0.832,
      "unique_values": 2
    },
    "is_early_morning": {
      "auc": 0.4392819429778247,
      "auc_std": 0.009390094992765916,
      "mean": 0.115,
      "std": 0.3190219428189855,
      "min": 0.0,
      "max": 1.0,
      "missing_rate": 0.0,
      "zero_rate": 0.885,
      "unique_values": 2
    },
    "is_late_evening": {
      "auc": 0.5037357295132593,
      "auc_std": 0.04040248285811467,
      "mean": 0.125,
      "std": 0.33071891388307384,
      "min": 0.0,
      "max": 1.0,
      "missing_rate": 0.0,
      "zero_rate": 0.875,
      "unique_values": 2
    },
    "temp_mean_30m": {
      "auc": 0.45408539379570045,
      "auc_std": 0.1077812100791443,
      "mean": 26.920706,
      "std": 2.8575374907247206,
      "min": 22.598333333333333,
      "max": 40.038333333333334,
      "missing_rate": 0.0,
      "zero_rate": 0.0,
      "unique_values": 922
    },
    "temp_std_30m": {
      "auc": 0.6890279133709231,
      "auc_std": 0.15429130556709583,
      "mean": 0.7783177860067808,
      "std": 0.5398571082413454,
      "min": 0.0,
      "max": 6.329543427451908,
      "missing_rate": 0.0,
      "zero_rate": 0.001,
      "unique_values": 1000
    },
    "temp_max_30m": {
      "auc": 0.5001095813990557,
      "auc_std": 0.19081747532542695,
      "mean": 27.942690000000002,
      "std": 3.043122781601163,
      "min": 23.28,
      "max": 41.18,
      "missing_rate": 0.0,
      "zero_rate": 0.0,
      "unique_values": 326
    },
    "temp_min_30m": {
      "auc": 0.41682771811679376,
      "auc_std": 0.1153443411757384,
      "mean": 25.89624,
      "std": 2.801376886889731,
      "min": 20.51,
      "max": 39.03,
      "missing_rate": 0.0,
      "zero_rate": 0.0,
      "unique_values": 329
    },
    "temp_diff_now_vs_mean_30m": {
      "auc": 0.4256141539319799,
      "auc_std": 0.045223900311645616,
      "mean": 0.001604000000000049,
      "std": 1.0464521886756222,
      "min": -8.621666666666666,
      "max": 8.341666666666669,
      "missing_rate": 0.0,
      "zero_rate": 0.002,
      "unique_values": 894
    },
    "temp_range_30m": {
      "auc": 0.678079735410731,
      "auc_std": 0.16331765389246064,
      "mean": 2.0464499999999997,
      "std": 1.2984628209925764,
      "min": 0.0,
      "max": 13.150000000000002,
      "missing_rate": 0.0,
      "zero_rate": 0.001,
      "unique_values": 341
    },
    "temp_zscore_30m": {
      "auc": 0.4299974098942042,
      "auc_std": 0.16558168812614193,
      "mean": 0.02507794620055003,
      "std": 1.0474012986341834,
      "min": -2.016706412777594,
      "max": 2.0254057581298337,
      "missing_rate": 0.0,
      "zero_rate": 0.002,
      "unique_values": 999
    },
    "temp_mean_60m": {
      "auc": 0.5209997808372019,
      "auc_std": 0.061408315700820164,
      "mean": 26.91680706746032,
      "std": 2.720766611663952,
      "min": 22.787499999999998,
      "max": 35.593333333333334,
      "missing_rate": 0.0,
      "zero_rate": 0.0,
      "unique_values": 981
    },
    "temp_std_60m": {
      "auc": 0.6853619174752444,
      "auc_std": 0.19103252373834764,
      "mean": 1.0972709373834946,
      "std": 0.6829340750555146,
      "min": 0.0,
      "max": 6.235804728025135,
      "missing_rate": 0.0,
      "zero_rate": 0.001,
      "unique_values": 999
    },
    "temp_max_60m": {
      "auc": 0.5904943117291944,
      "auc_std": 0.2169631385403515,
      "mean": 28.65597,
      "std": 3.110339798012429,
      "min": 23.28,
      "max": 41.18,
      "missing_rate": 0.0,
      "zero_rate": 0.0,
      "unique_values": 295
    },
    "temp_min_60m": {
      "auc": 0.45265087366260887,
      "auc_std": 0.061370499469050814,
      "mean": 25.189510000000002,
      "std": 2.639746552209132,
      "min": 20.51,
      "max": 30.53,
      "missing_rate": 0.0,
      "zero_rate": 0.0,
      "unique_values": 295
    },
    "temp_diff_now_vs_mean_60m": {
      "auc": 0.38490964515550596,
      "auc_std": 0.07914643020022168,
      "mean": 0.005502932539682529,
      "std": 1.6814675509563757,
      "min": -7.610833333333336,
      "max": 10.221666666666668,
      "missing_rate": 0.0,
      "zero_rate": 0.001,
      "unique_values": 967
    },
    "temp_range_60m": {
      "auc": 0.685670737781674,
      "auc_std": 0.2172416898898353,
      "mean": 3.46646,
      "std": 1.8492477574408466,
      "min": 0.0,
      "max": 14.02,
      "missing_rate": 0.0,
      "zero_rate": 0.001,
      "unique_values": 398
    },
    "temp_zscore_60m": {
      "auc": 0.4043752864059294,
      "auc_std": 0.21069133172928325,
      "mean": 0.023422671820386674,
      "std": 1.2759471374507174,
      "min": -2.9843309380504652,
      "max": 2.885961448055091,
      "missing_rate": 0.0,
      "zero_rate": 0.001,
      "unique_values": 1000
    },
    "temp_mean_120m": {
      "auc": 0.6045506166444183,
      "auc_std": 0.14259217993807613,
      "mean": 26.90175396321526,
      "std": 2.3398342316764262,
      "min": 23.28,
      "max": 32.03333333333333,
      "missing_rate": 0.0,
      "zero_rate": 0.0,
      "unique_values": 985
    },
    "temp_std_120m": {
      "auc": 0.60469008387958,
      "auc_std": 0.138188799732712,
      "mean": 1.7260460161357833,
      "std": 0.8268762613725189,
      "min": 0.0,
      "max": 5.933074437642637,
      "missing_rate": 0.0,
      "zero_rate": 0.001,
      "unique_values": 999
    },
    "temp_max_120m": {
      "auc": 0.6479448506704389,
      "auc_std": 0.18530868248919674,
      "mean": 29.93644,
      "std": 2.9773196547230194,
      "min": 23.28,
      "max": 41.18,
      "missing_rate": 0.0,
      "zero_rate": 0.0,
      "unique_values": 252
    },
    "temp_min_120m": {
      "auc": 0.5512342850311809,
      "auc_std": 0.05220050493421575,
      "mean": 23.97114,
      "std": 2.0847256655013386,
      "min": 20.51,
      "max": 29.62,
      "missing_rate": 0.0,
      "zero_rate": 0.0,
      "unique_values": 246
    },
    "temp_diff_now_vs_mean_120m": {
      "auc": 0.36199717080751526,
      "auc_std": 0.24133492462808723,
      "mean": 0.02055603678474052,
      "std": 2.7130117310667003,
      "min": -8.773333333333333,
      "max": 12.29333333333333,
      "missing_rate": 0.0,
      "zero_rate": 0.001,
      "unique_values": 993
    },
    "temp_range_120m": {
      "auc": 0.6164252555238987,
      "auc_std": 0.15264785329639383,
      "mean": 5.965299999999999,
      "std": 2.4541070290433544,
      "min": 0.0,
      "max": 17.38,
      "missing_rate": 0.0,
      "zero_rate": 0.001,
      "unique_values": 430
    },
    "temp_zscore_120m": {
      "auc": 0.3499631408021358,
      "auc_std": 0.20959959013317234,
      "mean": 0.04410025970135592,
      "std": 1.4834741855002207,
      "min": -3.571619888717867,
      "max": 3.7012119646897808,
      "missing_rate": 0.0,
      "zero_rate": 0.001,
      "unique_values": 1000
    },
    "temp_mean_360m": {
      "auc": 0.43640294076627284,
      "auc_std": 0.18020422398780933,
      "mean": 26.800815129931827,
      "std": 0.6609185085413546,
      "min": 23.28,
      "max": 28.18263888888889,
      "missing_rate": 0.0,
      "zero_rate": 0.0,
      "unique_values": 977
    },
    "temp_std_360m": {
      "auc": 0.6060648323404594,
      "auc_std": 0.21309806210260968,
      "mean": 2.8043183910105727,
      "std": 0.47737235564160224,
      "min": 0.0,
      "max": 4.441686956590298,
      "missing_rate": 0.0,
      "zero_rate": 0.001,
      "unique_values": 996
    },
    "temp_max_360m": {
      "auc": 0.6171126297543384,
      "auc_std": 0.19674852299481993,
      "mean": 31.842219999999998,
      "std": 2.0281498148805475,
      "min": 23.28,
      "max": 41.18,
      "missing_rate": 0.0,
      "zero_rate": 0.0,
      "unique_values": 50
    },
    "temp_min_360m": {
      "auc": 0.7308880078101652,
      "auc_std": 0.1868688796914829,
      "mean": 22.07424,
      "std": 0.6657299921139196,
      "min": 20.51,
      "max": 23.95,
      "missing_rate": 0.0,
      "zero_rate": 0.0,
      "unique_values": 29
    },
    "temp_diff_now_vs_mean_360m": {
      "auc": 0.40782211950349667,
      "auc_std": 0.1399890868574339,
      "mean": 0.12149487006816864,
      "std": 2.9721622623030273,
      "min": -6.3125,
      "max": 14.298194444444444,
      "missing_rate": 0.0,
      "zero_rate": 0.001,
      "unique_values": 993
    },
    "temp_range_360m": {
      "auc": 0.5031081269550318,
      "auc_std": 0.10730976530614326,
      "mean": 9.76798,
      "std": 2.1108148946793035,
      "min": 0.0,
      "max": 18.16,
      "missing_rate": 0.0,
      "zero_rate": 0.001,
      "unique_values": 80
    },
    "temp_zscore_360m": {
      "auc": 0.4009683010898368,
      "auc_std": 0.15029099243486577,
      "mean": 0.06171305015590166,
      "std": 1.062201588586002,
      "min": -2.509309116249662,
      "max": 4.759811649817066,
      "missing_rate": 0.0,
      "zero_rate": 0.001,
      "unique_values": 1000
    },
    "temp_velocity_5m": {
      "auc": 0.4730828236137952,
      "auc_std": 0.03883778165884872,
      "mean": 0.0009800000000000004,
      "std": 1.0206568667284808,
      "min": -10.629999999999999,
      "max": 9.130000000000003,
      "missing_rate": 0.0,
      "zero_rate": 0.006,
      "unique_values": 460
    },
    "temp_acceleration_5m": {
      "auc": 0.48936064234623733,
      "auc_std": 0.012585022599196277,
      "mean": 0.0004299999999999997,
      "std": 1.6100671772010007,
      "min": -11.280000000000001,
      "max": 8.400000000000006,
      "missing_rate": 0.0,
      "zero_rate": 0.002,
      "unique_values": 723
    },
    "temp_velocity_15m": {
      "auc": 0.4331653085214481,
      "auc_std": 0.048324052388918154,
      "mean": 0.00041000000000000194,
      "std": 0.48509107817215336,
      "min": -4.22,
      "max": 3.4,
      "missing_rate": 0.0,
      "zero_rate": 0.006,
      "unique_values": 542
    },
    "temp_acceleration_15m": {
      "auc": 0.4797672889561873,
      "auc_std": 0.019730944167967453,
      "mean": -0.0007933333333333352,
      "std": 0.47005559193685914,
      "min": -3.3099999999999987,
      "max": 3.673333333333332,
      "missing_rate": 0.0,
      "zero_rate": 0.005,
      "unique_values": 807
    },
    "temp_velocity_30m": {
      "auc": 0.39771074495427466,
      "auc_std": 0.06114442251392378,
      "mean": 0.0009499999999999992,
      "std": 0.35365805479618617,
      "min": -2.206666666666667,
      "max": 1.6900000000000002,
      "missing_rate": 0.0,
      "zero_rate": 0.006,
      "unique_values": 644
    },
    "temp_acceleration_30m": {
      "auc": 0.5274750453268515,
      "auc_std": 0.024805581511340342,
      "mean": -7.833333333333309e-05,
      "std": 0.23816066467244798,
      "min": -3.293333333333334,
      "max": 1.7133333333333336,
      "missing_rate": 0.0,
      "zero_rate": 0.008,
      "unique_values": 795
    },
    "temp_extreme_high": {
      "auc": 0.5566037735849056,
      "auc_std": 0.0,
      "mean": 0.006,
      "std": 0.0772269383052313,
      "min": 0.0,
      "max": 1.0,
      "missing_rate": 0.0,
      "zero_rate": 0.994,
      "unique_values": 2
    },
    "temp_very_high": {
      "auc": 0.562341854117272,
      "auc_std": 0.07481667254126045,
      "mean": 0.014,
      "std": 0.11749042514179611,
      "min": 0.0,
      "max": 1.0,
      "missing_rate": 0.0,
      "zero_rate": 0.986,
      "unique_values": 2
    },
    "temp_high": {
      "auc": 0.43144189197266436,
      "auc_std": 0.0910387801358477,
      "mean": 0.394,
      "std": 0.48863483297857513,
      "min": 0.0,
      "max": 1.0,
      "missing_rate": 0.0,
      "zero_rate": 0.606,
      "unique_values": 2
    },
    "temp_very_low": {
      "auc": 0.5,
      "auc_std": 0.0,
      "mean": 0.0,
      "std": 0.0,
      "min": 0.0,
      "max": 0.0,
      "missing_rate": 0.0,
      "zero_rate": 1.0,
      "unique_values": 1
    },
    "temp_stable_30m": {
      "auc": 0.4378773086808392,
      "auc_std": 0.0453133287096319,
      "mean": 0.212,
      "std": 0.4087248463208471,
      "min": 0.0,
      "max": 1.0,
      "missing_rate": 0.0,
      "zero_rate": 0.788,
      "unique_values": 2
    },
    "temp_volatile_30m": {
      "auc": 0.5895877747006435,
      "auc_std": 0.06666455441213189,
      "mean": 0.019,
      "std": 0.13652472303579305,
      "min": 0.0,
      "max": 1.0,
      "missing_rate": 0.0,
      "zero_rate": 0.981,
      "unique_values": 2
    },
    "temp_stable_60m": {
      "auc": 0.4767687434002112,
      "auc_std": 0.007338442928528729,
      "mean": 0.044,
      "std": 0.20509509989270833,
      "min": 0.0,
      "max": 1.0,
      "missing_rate": 0.0,
      "zero_rate": 0.956,
      "unique_values": 2
    },
    "temp_volatile_60m": {
      "auc": 0.637215835508358,
      "auc_std": 0.1193655054375439,
      "mean": 0.042,
      "std": 0.20058913230780975,
      "min": 0.0,
      "max": 1.0,
      "missing_rate": 0.0,
      "zero_rate": 0.958,
      "unique_values": 2
    },
    "temp_stable_120m": {
      "auc": 0.4978880675818374,
      "auc_std": 0.0014941600021599146,
      "mean": 0.004,
      "std": 0.063118935352238,
      "min": 0.0,
      "max": 1.0,
      "missing_rate": 0.0,
      "zero_rate": 0.996,
      "unique_values": 2
    },
    "temp_volatile_120m": {
      "auc": 0.6043115299555697,
      "auc_std": 0.0781342253358359,
      "mean": 0.293,
      "std": 0.4551384404771806,
      "min": 0.0,
      "max": 1.0,
      "missing_rate": 0.0,
      "zero_rate": 0.707,
      "unique_values": 2
    },
    "fridge_mean_30m": {
      "auc": 0.4431969875077205,
      "auc_std": 0.155504553489146,
      "mean": 156.6329095,
      "std": 23.467777329541644,
      "min": 4.931666666666667,
      "max": 394.61833333333334,
      "missing_rate": 0.0,
      "zero_rate": 0.0,
      "unique_values": 970
    },
    "fridge_std_30m": {
      "auc": 0.5300751130680799,
      "auc_std": 0.15440954966311635,
      "mean": 7.516090140165212,
      "std": 12.96576804974981,
      "min": 0.0,
      "max": 133.9190655209333,
      "missing_rate": 0.0,
      "zero_rate": 0.001,
      "unique_values": 998
    },
    "fridge_median_30m": {
      "auc": 0.4365324460560658,
      "auc_std": 0.15874669806199712,
      "mean": 156.583005,
      "std": 25.214454100673585,
      "min": 4.96,
      "max": 387.08500000000004,
      "missing_rate": 0.0,
      "zero_rate": 0.0,
      "unique_values": 618
    },
    "fridge_mean_60m": {
      "auc": 0.46622900520013544,
      "auc_std": 0.13536649263117354,
      "mean": 156.64983522186148,
      "std": 20.213238622571474,
      "min": 5.1450000000000005,
      "max": 277.7391666666667,
      "missing_rate": 0.0,
      "zero_rate": 0.0,
      "unique_values": 981
    },
    "fridge_std_60m": {
      "auc": 0.6364288418242315,
      "auc_std": 0.13003247921469877,
      "mean": 9.679992982526473,
      "std": 16.29026794041063,
      "min": 0.0,
      "max": 128.42980028900155,
      "missing_rate": 0.0,
      "zero_rate": 0.001,
      "unique_values": 1000
    },
    "fridge_median_60m": {
      "auc": 0.46701599888426215,
      "auc_std": 0.1313858227099341,
      "mean": 155.920165,
      "std": 20.89134406154317,
      "min": 5.415,
      "max": 270.97,
      "missing_rate": 0.0,
      "zero_rate": 0.0,
      "unique_values": 552
    },
    "fridge_mean_120m": {
      "auc": 0.4417325815385228,
      "auc_std": 0.19608107427636712,
      "mean": 156.65945587990547,
      "std": 16.034874563288977,
      "min": 66.97416666666668,
      "max": 222.56916666666666,
      "missing_rate": 0.0,
      "zero_rate": 0.0,
      "unique_values": 994
    },
    "fridge_std_120m": {
      "auc": 0.6780299256838875,
      "auc_std": 0.2696748781906235,
      "mean": 12.149522312608552,
      "std": 18.813819433317754,
      "min": 0.0,
      "max": 107.26162992583976,
      "missing_rate": 0.0,
      "zero_rate": 0.001,
      "unique_values": 1000
    },
    "fridge_median_120m": {
      "auc": 0.4957761351636748,
      "auc_std": 0.15401381363962705,
      "mean": 155.16476,
      "std": 18.19742258239886,
      "min": 6.09,
      "max": 169.325,
      "missing_rate": 0.0,
      "zero_rate": 0.0,
      "unique_values": 513
    },
    "fridge_mean_360m": {
      "auc": 0.5507859974895898,
      "auc_std": 0.06200594960981725,
      "mean": 156.5613343431802,
      "std": 9.287044313926287,
      "min": 127.44666666666666,
      "max": 179.27375,
      "missing_rate": 0.0,
      "zero_rate": 0.0,
      "unique_values": 988
    },
    "fridge_std_360m": {
      "auc": 0.7455719152836167,
      "auc_std": 0.0857708463609089,
      "mean": 16.939496762011366,
      "std": 19.329013865065477,
      "min": 0.0,
      "max": 66.61138803979699,
      "missing_rate": 0.0,
      "zero_rate": 0.001,
      "unique_values": 999
    },
    "fridge_median_360m": {
      "auc": 0.5771751907712539,
      "auc_std": 0.15725775581927876,
      "mean": 157.012815,
      "std": 1.3828447131818509,
      "min": 147.41,
      "max": 160.52499999999998,
      "missing_rate": 0.0,
      "zero_rate": 0.0,
      "unique_values": 219
    },
    "fridge_power_ratio_6h": {
      "auc": 0.4042358191707677,
      "auc_std": 0.17091415954980735,
      "mean": 0.9971891690479674,
      "std": 0.1707969516411161,
      "min": 0.024620355411954765,
      "max": 2.667086098965051,
      "missing_rate": 0.0,
      "zero_rate": 0.0,
      "unique_values": 992
    },
    "fridge_power_ratio_1h": {
      "auc": 0.4089577812755275,
      "auc_std": 0.14351280196315955,
      "mean": 1.0109088983749623,
      "std": 0.32995178060402913,
      "min": 0.0384930576693437,
      "max": 8.764469414442777,
      "missing_rate": 0.0,
      "zero_rate": 0.0,
      "unique_values": 1000
    },
    "fridge_cv_30m": {
      "auc": 0.6937100276942081,
      "auc_std": 0.2057653203660568,
      "mean": 0.05292985481994017,
      "std": 0.1285240993207465,
      "min": 0.0,
      "max": 2.0162517049650384,
      "missing_rate": 0.0,
      "zero_rate": 0.001,
      "unique_values": 998
    },
    "fridge_cv_60m": {
      "auc": 0.6895857823115699,
      "auc_std": 0.17502324946630876,
      "mean": 0.07322107198261706,
      "std": 0.19069938820911606,
      "min": 0.0,
      "max": 2.44559638963094,
      "missing_rate": 0.0,
      "zero_rate": 0.001,
      "unique_values": 1000
    },
    "fridge_cv_120m": {
      "auc": 0.673327887469865,
      "auc_std": 0.2780764518135046,
      "mean": 0.08538152287545747,
      "std": 0.16260431787571292,
      "min": 0.0,
      "max": 1.1156929056440368,
      "missing_rate": 0.0,
      "zero_rate": 0.001,
      "unique_values": 1000
    },
    "fridge_diff_5m": {
      "auc": 0.4743778765117253,
      "auc_std": 0.04279968206613151,
      "mean": -0.0037799999999999444,
      "std": 14.355963378039108,
      "min": -235.01000000000002,
      "max": 259.46000000000004,
      "missing_rate": 0.0,
      "zero_rate": 0.001,
      "unique_values": 859
    },
    "fridge_pct_change_5m": {
      "auc": 0.4831742742722799,
      "auc_std": 0.05071154045087508,
      "mean": 0.03193321022192502,
      "std": 0.9812869300035265,
      "min": -0.9651864557524935,
      "max": 30.949152542372886,
      "missing_rate": 0.0,
      "zero_rate": 0.001,
      "unique_values": 1000
    },
    "fridge_diff_15m": {
      "auc": 0.4665776732880397,
      "auc_std": 0.04862762509073662,
      "mean": -0.03780000000000021,
      "std": 23.99837729014193,
      "min": -259.62,
      "max": 260.43,
      "missing_rate": 0.0,
      "zero_rate": 0.003,
      "unique_values": 933
    },
    "fridge_pct_change_15m": {
      "auc": 0.42878205255922375,
      "auc_std": 0.08687056119898288,
      "mean": 0.0976778558470419,
      "std": 1.7900973829937779,
      "min": -0.9629228687415426,
      "max": 38.69478908188585,
      "missing_rate": 0.0,
      "zero_rate": 0.003,
      "unique_values": 998
    },
    "fridge_diff_30m": {
      "auc": 0.4800761092626168,
      "auc_std": 0.03578070932296045,
      "mean": -0.07620999999999983,
      "std": 32.77377667184391,
      "min": -271.52,
      "max": 275.11,
      "missing_rate": 0.0,
      "zero_rate": 0.008,
      "unique_values": 922
    },
    "fridge_pct_change_30m": {
      "auc": 0.4543444043752864,
      "auc_std": 0.1291906706832255,
      "mean": 0.1867574348466617,
      "std": 2.4269325812123284,
      "min": -0.9731910297948034,
      "max": 38.58005249343832,
      "missing_rate": 0.0,
      "zero_rate": 0.008,
      "unique_values": 993
    },
    "fridge_spike_30m": {
      "auc": 0.5089059791596103,
      "auc_std": 0.01273693451556691,
      "mean": 0.002,
      "std": 0.044676615807377355,
      "min": 0.0,
      "max": 1.0,
      "missing_rate": 0.0,
      "zero_rate": 0.998,
      "unique_values": 2
    },
    "fridge_spike_60m": {
      "auc": 0.5015142156960412,
      "auc_std": 0.005775378696563946,
      "mean": 0.016,
      "std": 0.125475097130865,
      "min": 0.0,
      "max": 1.0,
      "missing_rate": 0.0,
      "zero_rate": 0.984,
      "unique_values": 2
    },
    "fridge_power_very_low": {
      "auc": 0.6320754716981132,
      "auc_std": 0.17406541652295196,
      "mean": 0.014,
      "std": 0.11749042514179614,
      "min": 0.0,
      "max": 1.0,
      "missing_rate": 0.0,
      "zero_rate": 0.986,
      "unique_values": 2
    },
    "fridge_power_low": {
      "auc": 0.6320754716981132,
      "auc_std": 0.17406541652295196,
      "mean": 0.014,
      "std": 0.11749042514179614,
      "min": 0.0,
      "max": 1.0,
      "missing_rate": 0.0,
      "zero_rate": 0.986,
      "unique_values": 2
    },
    "fridge_power_normal": {
      "auc": 0.31237672092606245,
      "auc_std": 0.15611374696050426,
      "mean": 0.978,
      "std": 0.14668333238647122,
      "min": 0.0,
      "max": 1.0,
      "missing_rate": 0.0,
      "zero_rate": 0.022,
      "unique_values": 2
    },
    "fridge_power_high": {
      "auc": 0.5555478073758243,
      "auc_std": 0.07782034297225145,
      "mean": 0.008,
      "std": 0.08908422980528033,
      "min": 0.0,
      "max": 1.0,
      "missing_rate": 0.0,
      "zero_rate": 0.992,
      "unique_values": 2
    },
    "fridge_power_very_high": {
      "auc": 0.5566037735849056,
      "auc_std": 0.0,
      "mean": 0.006,
      "std": 0.07722693830523131,
      "min": 0.0,
      "max": 1.0,
      "missing_rate": 0.0,
      "zero_rate": 0.994,
      "unique_values": 2
    },
    "motion_streak": {
      "auc": 0.7004144169273375,
      "auc_std": 0.06291627709538687,
      "mean": 0.571,
      "std": 1.5056423878198968,
      "min": 0.0,
      "max": 16.0,
      "missing_rate": 0.0,
      "zero_rate": 0.746,
      "unique_values": 17
    },
    "time_since_last_motion": {
      "auc": 0.3173078838835648,
      "auc_std": 0.031440960799367076,
      "mean": 5.375,
      "std": 6.495873690274466,
      "min": 0.0,
      "max": 30.0,
      "missing_rate": 0.0,
      "zero_rate": 0.254,
      "unique_values": 31
    },
    "motion_rate_30m": {
      "auc": 0.6921161164352174,
      "auc_std": 0.07039524413029107,
      "mean": 0.25399999999999995,
      "std": 0.25295058806019804,
      "min": 0.0,
      "max": 1.0,
      "missing_rate": 0.0,
      "zero_rate": 0.34,
      "unique_values": 7
    },
    "motion_sum_30m": {
      "auc": 0.6921161164352174,
      "auc_std": 0.07039524413029107,
      "mean": 1.524,
      "std": 1.5177035283611884,
      "min": 0.0,
      "max": 6.0,
      "missing_rate": 0.0,
      "zero_rate": 0.34,
      "unique_values": 7
    },
    "motion_rate_60m": {
      "auc": 0.6913490466418282,
      "auc_std": 0.10679955840667131,
      "mean": 0.2531666666666667,
      "std": 0.1959406797987595,
      "min": 0.0,
      "max": 1.0,
      "missing_rate": 0.0,
      "zero_rate": 0.176,
      "unique_values": 13
    },
    "motion_sum_60m": {
      "auc": 0.6913490466418282,
      "auc_std": 0.10679955840667131,
      "mean": 3.038,
      "std": 2.351288157585114,
      "min": 0.0,
      "max": 12.0,
      "missing_rate": 0.0,
      "zero_rate": 0.176,
      "unique_values": 13
    },
    "motion_rate_180m": {
      "auc": 0.7082345440417604,
      "auc_std": 0.1413554486241561,
      "mean": 0.24650244279817707,
      "std": 0.10953036340560772,
      "min": 0.0,
      "max": 0.5833333333333334,
      "missing_rate": 0.0,
      "zero_rate": 0.025,
      "unique_values": 31
    },
    "motion_sum_180m": {
      "auc": 0.7082345440417604,
      "auc_std": 0.1413554486241561,
      "mean": 8.872,
      "std": 3.9471022282175565,
      "min": 0.0,
      "max": 21.0,
      "missing_rate": 0.0,
      "zero_rate": 0.025,
      "unique_values": 22
    },
    "motion_rate_360m": {
      "auc": 0.524615967006037,
      "auc_std": 0.09716151729916679,
      "mean": 0.24019153516503014,
      "std": 0.08029419686486455,
      "min": 0.0,
      "max": 0.5,
      "missing_rate": 0.0,
      "zero_rate": 0.025,
      "unique_values": 73
    },
    "motion_sum_360m": {
      "auc": 0.5249546731485725,
      "auc_std": 0.09787859713305484,
      "mean": 17.207,
      "std": 5.946944677731582,
      "min": 0.0,
      "max": 36.0,
      "missing_rate": 0.0,
      "zero_rate": 0.025,
      "unique_values": 37
    },
    "night_motion": {
      "auc": 0.6456635651810085,
      "auc_std": 0.13815095388305115,
      "mean": 0.026,
      "std": 0.15913516267626082,
      "min": 0.0,
      "max": 1.0,
      "missing_rate": 0.0,
      "zero_rate": 0.974,
      "unique_values": 2
    },
    "door_open_streak": {
      "auc": 0.6041820246657768,
      "auc_std": 0.040722118897945844,
      "mean": 0.048,
      "std": 0.30934770081576496,
      "min": 0.0,
      "max": 4.0,
      "missing_rate": 0.0,
      "zero_rate": 0.969,
      "unique_values": 5
    },
    "time_since_door_opened": {
      "auc": 0.2559423004124245,
      "auc_std": 0.15978005589027253,
      "mean": 49.568,
      "std": 44.88228354261846,
      "min": 0.0,
      "max": 183.0,
      "missing_rate": 0.0,
      "zero_rate": 0.031,
      "unique_values": 184
    },
    "door_open_rate_30m": {
      "auc": 0.6855810802733558,
      "auc_std": 0.14848906514027838,
      "mean": 0.031,
      "std": 0.09709731658953756,
      "min": 0.0,
      "max": 0.8333333333333334,
      "missing_rate": 0.0,
      "zero_rate": 0.877,
      "unique_values": 6
    },
    "door_open_rate_60m": {
      "auc": 0.6646012233268913,
      "auc_std": 0.16880615998423937,
      "mean": 0.030999999999999996,
      "std": 0.07451770855903239,
      "min": 0.0,
      "max": 0.5,
      "missing_rate": 0.0,
      "zero_rate": 0.776,
      "unique_values": 7
    },
    "door_open_rate_180m": {
      "auc": 0.8293618377796816,
      "auc_std": 0.19339760270339565,
      "mean": 0.03088888888888889,
      "std": 0.05076160695585534,
      "min": 0.0,
      "max": 0.2777777777777778,
      "missing_rate": 0.0,
      "zero_rate": 0.524,
      "unique_values": 11
    },
    "window_open_streak": {
      "auc": 0.5986132972046782,
      "auc_std": 0.07518060374802044,
      "mean": 0.466,
      "std": 1.0586992018510262,
      "min": 0.0,
      "max": 9.0,
      "missing_rate": 0.0,
      "zero_rate": 0.746,
      "unique_values": 10
    },
    "time_since_window_opened": {
      "auc": 0.39584786117032933,
      "auc_std": 0.11775811082876704,
      "mean": 4.335,
      "std": 5.031577784353532,
      "min": 0.0,
      "max": 28.0,
      "missing_rate": 0.0,
      "zero_rate": 0.254,
      "unique_values": 29
    },
    "window_open_rate_30m": {
      "auc": 0.5893984977386384,
      "auc_std": 0.13577273817393531,
      "mean": 0.25393333333333334,
      "std": 0.23767409058063804,
      "min": 0.0,
      "max": 1.0,
      "missing_rate": 0.0,
      "zero_rate": 0.303,
      "unique_values": 8
    },
    "window_open_rate_60m": {
      "auc": 0.5774939730230519,
      "auc_std": 0.1240423746888432,
      "mean": 0.2544275613275613,
      "std": 0.17952248001192533,
      "min": 0.0,
      "max": 0.8333333333333334,
      "missing_rate": 0.0,
      "zero_rate": 0.101,
      "unique_values": 15
    },
    "window_open_rate_120m": {
      "auc": 0.5292482716024786,
      "auc_std": 0.1161863221107198,
      "mean": 0.2533390463248183,
      "std": 0.12743886051083259,
      "min": 0.0,
      "max": 0.625,
      "missing_rate": 0.0,
      "zero_rate": 0.006,
      "unique_values": 28
    },
    "temp_when_window_open": {
      "auc": 0.5621226913191608,
      "auc_std": 0.06796807996243062,
      "mean": 6.85687,
      "std": 11.83151916294353,
      "min": 0.0,
      "max": 40.32,
      "missing_rate": 0.0,
      "zero_rate": 0.746,
      "unique_values": 233
    },
    "temp_when_window_closed": {
      "auc": 0.39693371321551674,
      "auc_std": 0.056544666526268154,
      "mean": 20.06544,
      "std": 12.003799173861582,
      "min": 0.0,
      "max": 41.18,
      "missing_rate": 0.0,
      "zero_rate": 0.254,
      "unique_values": 509
    },
    "temp_change_with_window_5m": {
      "auc": 0.5185292183857664,
      "auc_std": 0.09142296028263505,
      "mean": 0.19912,
      "std": 0.45597897495388967,
      "min": 0.0,
      "max": 6.629999999999999,
      "missing_rate": 0.0,
      "zero_rate": 0.704,
      "unique_values": 173
    },
    "temp_change_with_window_15m": {
      "auc": 0.5686577274810225,
      "auc_std": 0.06774667999266527,
      "mean": 0.35409999999999997,
      "std": 0.8487104276489126,
      "min": 0.0,
      "max": 12.66,
      "missing_rate": 0.0,
      "zero_rate": 0.668,
      "unique_values": 221
    },
    "temp_change_with_window_30m": {
      "auc": 0.6242951923651652,
      "auc_std": 0.04966123211557033,
      "mean": 0.67835,
      "std": 1.3348229760908372,
      "min": 0.0,
      "max": 13.240000000000002,
      "missing_rate": 0.0,
      "zero_rate": 0.623,
      "unique_values": 284
    },
    "motion_with_door_open": {
      "auc": 0.5712478332768823,
      "auc_std": 0.06971071798294591,
      "mean": 0.016,
      "std": 0.125475097130865,
      "min": 0.0,
      "max": 1.0,
      "missing_rate": 0.0,
      "zero_rate": 0.984,
      "unique_values": 2
    },
    "motion_with_door_closed": {
      "auc": 0.5935028192305393,
      "auc_std": 0.05223849553348165,
      "mean": 0.238,
      "std": 0.4258591316386206,
      "min": 0.0,
      "max": 1.0,
      "missing_rate": 0.0,
      "zero_rate": 0.762,
      "unique_values": 2
    },
    "motion_with_window_open": {
      "auc": 0.6165547608136916,
      "auc_std": 0.034110791234222816,
      "mean": 0.1,
      "std": 0.3,
      "min": 0.0,
      "max": 1.0,
      "missing_rate": 0.0,
      "zero_rate": 0.9,
      "unique_values": 2
    },
    "door_and_window_open": {
      "auc": 0.4968321013727561,
      "auc_std": 0.0012898748386359624,
      "mean": 0.006,
      "std": 0.0772269383052313,
      "min": 0.0,
      "max": 1.0,
      "missing_rate": 0.0,
      "zero_rate": 0.994,
      "unique_values": 2
    },
    "door_or_window_open": {
      "auc": 0.6913988563686716,
      "auc_std": 0.10495323717444754,
      "mean": 0.279,
      "std": 0.4485075250204839,
      "min": 0.0,
      "max": 1.0,
      "missing_rate": 0.0,
      "zero_rate": 0.721,
      "unique_values": 2
    },
    "power_temp_ratio": {
      "auc": 0.4635492418959575,
      "auc_std": 0.11091155927366639,
      "mean": 5.836922811594932,
      "std": 1.0689212271796849,
      "min": 0.16443677168752696,
      "max": 15.131069733479372,
      "missing_rate": 0.0,
      "zero_rate": 0.0,
      "unique_values": 1000
    },
    "temp_power_interaction": {
      "auc": 0.3948715905241976,
      "auc_std": 0.18969440013941355,
      "mean": 4.2359152926000005,
      "std": 0.9524109191551382,
      "min": 0.0878967,
      "max": 12.5395536,
      "missing_rate": 0.0,
      "zero_rate": 0.0,
      "unique_values": 1000
    }
  },
  "feature_groups": {
    "time_features": [
      "hour",
      "day_of_week",
      "month",
      "day_of_year",
      "hour_sin",
      "hour_cos",
      "day_of_week_sin",
      "day_of_week_cos",
      "month_sin",
      "month_cos",
      "is_weekend",
      "is_night",
      "is_business_hours",
      "is_peak_hours",
      "night_motion"
    ],
    "temperature_features": [
      "temperature_living_room",
      "temp_mean_30m",
      "temp_std_30m",
      "temp_max_30m",
      "temp_min_30m",
      "temp_diff_now_vs_mean_30m",
      "temp_range_30m",
      "temp_zscore_30m",
      "temp_mean_60m",
      "temp_std_60m",
      "temp_max_60m",
      "temp_min_60m",
      "temp_diff_now_vs_mean_60m",
      "temp_range_60m",
      "temp_zscore_60m",
      "temp_mean_120m",
      "temp_std_120m",
      "temp_max_120m",
      "temp_min_120m",
      "temp_diff_now_vs_mean_120m",
      "temp_range_120m",
      "temp_zscore_120m",
      "temp_mean_360m",
      "temp_std_360m",
      "temp_max_360m",
      "temp_min_360m",
      "temp_diff_now_vs_mean_360m",
      "temp_range_360m",
      "temp_zscore_360m",
      "temp_velocity_5m",
      "temp_acceleration_5m",
      "temp_velocity_15m",
      "temp_acceleration_15m",
      "temp_velocity_30m",
      "temp_acceleration_30m",
      "temp_extreme_high",
      "temp_very_high",
      "temp_high",
      "temp_very_low",
      "temp_stable_30m",
      "temp_volatile_30m",
      "temp_stable_60m",
      "temp_volatile_60m",
      "temp_stable_120m",
      "temp_volatile_120m",
      "temp_when_window_open",
      "temp_when_window_closed",
      "temp_change_with_window_5m",
      "temp_change_with_window_15m",
      "temp_change_with_window_30m",
      "power_temp_ratio",
      "temp_power_interaction"
    ],
    "fridge_features": [
      "power_consumption_fridge",
      "fridge_mean_30m",
      "fridge_std_30m",
      "fridge_median_30m",
      "fridge_mean_60m",
      "fridge_std_60m",
      "fridge_median_60m",
      "fridge_mean_120m",
      "fridge_std_120m",
      "fridge_median_120m",
      "fridge_mean_360m",
      "fridge_std_360m",
      "fridge_median_360m",
      "fridge_power_ratio_6h",
      "fridge_power_ratio_1h",
      "fridge_cv_30m",
      "fridge_cv_60m",
      "fridge_cv_120m",
      "fridge_diff_5m",
      "fridge_pct_change_5m",
      "fridge_diff_15m",
      "fridge_pct_change_15m",
      "fridge_diff_30m",
      "fridge_pct_change_30m",
      "fridge_spike_30m",
      "fridge_spike_60m",
      "fridge_power_very_low",
      "fridge_power_low",
      "fridge_power_normal",
      "fridge_power_high",
      "fridge_power_very_high"
    ],
    "motion_features": [
      "motion_detected_hallway",
      "motion_streak",
      "time_since_last_motion",
      "motion_rate_30m",
      "motion_sum_30m",
      "motion_rate_60m",
      "motion_sum_60m",
      "motion_rate_180m",
      "motion_sum_180m",
      "motion_rate_360m",
      "motion_sum_360m",
      "motion_with_door_open",
      "motion_with_door_closed",
      "motion_with_window_open"
    ],
    "door_window_features": [
      "window_open",
      "door_state_front",
      "door_open_streak",
      "time_since_door_opened",
      "door_open_rate_30m",
      "door_open_rate_60m",
      "door_open_rate_180m",
      "window_open_streak",
      "time_since_window_opened",
      "window_open_rate_30m",
      "window_open_rate_60m",
      "window_open_rate_120m",
      "door_and_window_open",
      "door_or_window_open"
    ],
    "cross_sensor_features": [],
    "original_features": [
      "is_early_morning",
      "is_late_evening"
    ]
  },
  "feature_ranking": [
    {
      "feature": "fridge_std_360m",
      "auc": 0.7455719152836167,
      "auc_std": 0.0857708463609089,
      "stability": 0.9142291536390911,
      "discriminative_power": 0.4911438305672333,
      "data_quality": 0.999,
      "uniqueness": 1.0,
      "composite_score": 0.7705262783186206
    },
    {
      "feature": "time_since_door_opened",
      "auc": 0.2559423004124245,
      "auc_std": 0.15978005589027253,
      "stability": 0.8402199441097274,
      "discriminative_power": 0.488115399175151,
      "data_quality": 0.969,
      "uniqueness": 1.0,
      "composite_score": 0.7411121429029787
    },
    {
      "feature": "day_of_year",
      "auc": 0.7925823354784722,
      "auc_std": 0.035916534917411945,
      "stability": 0.964083465082588,
      "discriminative_power": 0.5851646709569445,
      "data_quality": 1.0,
      "uniqueness": 0.14,
      "composite_score": 0.7372909079075542
    },
    {
      "feature": "temp_std_30m",
      "auc": 0.6890279133709231,
      "auc_std": 0.15429130556709583,
      "stability": 0.8457086944329042,
      "discriminative_power": 0.3780558267418461,
      "data_quality": 0.999,
      "uniqueness": 1.0,
      "composite_score": 0.7047349390266097
    },
    {
      "feature": "fridge_cv_60m",
      "auc": 0.6895857823115699,
      "auc_std": 0.17502324946630876,
      "stability": 0.8249767505336912,
      "discriminative_power": 0.3791715646231397,
      "data_quality": 0.999,
      "uniqueness": 1.0,
      "composite_score": 0.6989616510093632
    },
    {
      "feature": "temp_range_30m",
      "auc": 0.678079735410731,
      "auc_std": 0.16331765389246064,
      "stability": 0.8366823461075393,
      "discriminative_power": 0.35615947082146193,
      "data_quality": 0.999,
      "uniqueness": 1.0,
      "composite_score": 0.6932684921608465
    },
    {
      "feature": "fridge_cv_30m",
      "auc": 0.6937100276942081,
      "auc_std": 0.2057653203660568,
      "stability": 0.7942346796339432,
      "discriminative_power": 0.3874200553884162,
      "data_quality": 0.999,
      "uniqueness": 1.0,
      "composite_score": 0.6930384260455494
    },
    {
      "feature": "temp_std_60m",
      "auc": 0.6853619174752444,
      "auc_std": 0.19103252373834764,
      "stability": 0.8089674762616523,
      "discriminative_power": 0.3707238349504889,
      "data_quality": 0.999,
      "uniqueness": 1.0,
      "composite_score": 0.6907797768586912
    },
    {
      "feature": "temp_range_60m",
      "auc": 0.685670737781674,
      "auc_std": 0.2172416898898353,
      "stability": 0.7827583101101647,
      "discriminative_power": 0.37134147556334796,
      "data_quality": 0.999,
      "uniqueness": 1.0,
      "composite_score": 0.6831640832583885
    },
    {
      "feature": "fridge_std_60m",
      "auc": 0.6364288418242315,
      "auc_std": 0.13003247921469877,
      "stability": 0.8699675207853013,
      "discriminative_power": 0.2728576836484631,
      "data_quality": 0.999,
      "uniqueness": 1.0,
      "composite_score": 0.6699333296949755
    },
    {
      "feature": "temp_diff_now_vs_mean_60m",
      "auc": 0.38490964515550596,
      "auc_std": 0.07914643020022168,
      "stability": 0.9208535697997783,
      "discriminative_power": 0.23018070968898807,
      "data_quality": 0.999,
      "uniqueness": 1.0,
      "composite_score": 0.6681283548155287
    },
    {
      "feature": "temp_max_120m",
      "auc": 0.6479448506704389,
      "auc_std": 0.18530868248919674,
      "stability": 0.8146913175108033,
      "discriminative_power": 0.2958897013408779,
      "data_quality": 1.0,
      "uniqueness": 1.0,
      "composite_score": 0.6627632757895922
    },
    {
      "feature": "temp_velocity_30m",
      "auc": 0.39771074495427466,
      "auc_std": 0.06114442251392378,
      "stability": 0.9388555774860762,
      "discriminative_power": 0.20457851009145067,
      "data_quality": 0.994,
      "uniqueness": 1.0,
      "composite_score": 0.6622880772824031
    },
    {
      "feature": "fridge_std_120m",
      "auc": 0.6780299256838875,
      "auc_std": 0.2696748781906235,
      "stability": 0.7303251218093765,
      "discriminative_power": 0.35605985136777507,
      "data_quality": 0.999,
      "uniqueness": 1.0,
      "composite_score": 0.661321477089923
    },
    {
      "feature": "temp_min_360m",
      "auc": 0.7308880078101652,
      "auc_std": 0.1868688796914829,
      "stability": 0.8131311203085171,
      "discriminative_power": 0.4617760156203303,
      "data_quality": 1.0,
      "uniqueness": 0.29,
      "composite_score": 0.6576497423406873
    },
    {
      "feature": "temp_zscore_120m",
      "auc": 0.3499631408021358,
      "auc_std": 0.20959959013317234,
      "stability": 0.7904004098668277,
      "discriminative_power": 0.3000737183957284,
      "data_quality": 0.999,
      "uniqueness": 1.0,
      "composite_score": 0.6569496103183396
    },
    {
      "feature": "fridge_cv_120m",
      "auc": 0.673327887469865,
      "auc_std": 0.2780764518135046,
      "stability": 0.7219235481864954,
      "discriminative_power": 0.3466557749397301,
      "data_quality": 0.999,
      "uniqueness": 1.0,
      "composite_score": 0.6550393744318407
    },
    {
      "feature": "motion_rate_180m",
      "auc": 0.7082345440417604,
      "auc_std": 0.1413554486241561,
      "stability": 0.8586445513758438,
      "discriminative_power": 0.4164690880835209,
      "data_quality": 0.975,
      "uniqueness": 0.31,
      "composite_score": 0.6501810006461616
    },
    {
      "feature": "temp_range_120m",
      "auc": 0.6164252555238987,
      "auc_std": 0.15264785329639383,
      "stability": 0.8473521467036061,
      "discriminative_power": 0.23285051104779741,
      "data_quality": 0.999,
      "uniqueness": 1.0,
      "composite_score": 0.6471458484302007
    },
    {
      "feature": "temp_diff_now_vs_mean_30m",
      "auc": 0.4256141539319799,
      "auc_std": 0.045223900311645616,
      "stability": 0.9547760996883544,
      "discriminative_power": 0.14877169213604025,
      "data_quality": 0.998,
      "uniqueness": 1.0,
      "composite_score": 0.6455415067609224
    }
  ]
}